{
    "key": "group_5e42a18cb16e0",
    "title": "Options du site - Général",
    "fields": [
        {
            "key": "field_5e42ab658031a",
            "label": "Réglages généraux",
            "name": "",
            "type": "tab",
            "instructions": "",
            "required": 0,
            "conditional_logic": 0,
            "wrapper": {
                "width": "",
                "class": "",
                "id": ""
            },
            "placement": "top",
            "endpoint": 0
        },
        {
            "key": "field_5e42ab8d8031b",
            "label": "Couleur de la barre d'adresse du navigateur",
            "name": "theme_color",
            "type": "color_picker",
            "instructions": "Supporté sur mobile Chrome et Windows Phone.",
            "required": 0,
            "conditional_logic": 0,
            "wrapper": {
                "width": "",
                "class": "",
                "id": ""
            },
            "default_value": ""
        },
        {
            "key": "field_60b513684729b",
            "label": "Image à la une par défaut",
            "name": "default_featured_image",
            "type": "image",
            "instructions": "Image à afficher si un article ou une référence n'a pas d'image à la une renseignée.",
            "required": 1,
            "conditional_logic": 0,
            "wrapper": {
                "width": "",
                "class": "",
                "id": ""
            },
            "return_format": "array",
            "preview_size": "medium",
            "library": "all",
            "min_width": "",
            "min_height": "",
            "min_size": "",
            "max_width": "",
            "max_height": "",
            "max_size": "",
            "mime_types": ""
        },
        {
            "key": "field_6231b222a4a4d",
            "label": "Code Google Analytics (ID)",
            "name": "code_ga",
            "type": "text",
            "instructions": "",
            "required": 0,
            "conditional_logic": 0,
            "wrapper": {
                "width": "",
                "class": "",
                "id": ""
            },
            "default_value": "",
            "placeholder": "G-XXXXXXX",
            "prepend": "",
            "append": "",
            "maxlength": ""
        },
        {
            "key": "field_6214ed349d5fa",
            "label": "Footer",
            "name": "",
            "type": "tab",
            "instructions": "",
            "required": 0,
            "conditional_logic": 0,
            "wrapper": {
                "width": "",
                "class": "",
                "id": ""
            },
            "placement": "top",
            "endpoint": 0
        },
        {
            "key": "field_6214ed489d5fb",
            "label": "Informations du footer",
            "name": "footer",
            "type": "group",
            "instructions": "",
            "required": 0,
            "conditional_logic": 0,
            "wrapper": {
                "width": "",
                "class": "",
                "id": ""
            },
            "layout": "row",
            "sub_fields": [
                {
                    "key": "field_6214ed609d5fc",
                    "label": "Texte",
                    "name": "text",
                    "type": "textarea",
                    "instructions": "",
                    "required": 1,
                    "conditional_logic": 0,
                    "wrapper": {
                        "width": "",
                        "class": "",
                        "id": ""
                    },
                    "default_value": "",
                    "placeholder": "",
                    "maxlength": "",
                    "rows": 2,
                    "new_lines": ""
                },
                {
                    "key": "field_6214ed9c9d5fe",
                    "label": "Adresse",
                    "name": "address",
                    "type": "textarea",
                    "instructions": "",
                    "required": 1,
                    "conditional_logic": 0,
                    "wrapper": {
                        "width": "",
                        "class": "",
                        "id": ""
                    },
                    "default_value": "",
                    "placeholder": "",
                    "maxlength": "",
                    "rows": 2,
                    "new_lines": "br"
                },
                {
                    "key": "field_6214edbd9d5ff",
                    "label": "Téléphone",
                    "name": "phone",
                    "type": "text",
                    "instructions": "",
                    "required": 1,
                    "conditional_logic": 0,
                    "wrapper": {
                        "width": "",
                        "class": "",
                        "id": ""
                    },
                    "default_value": "",
                    "placeholder": "",
                    "prepend": "",
                    "append": "",
                    "maxlength": ""
                },
                {
                    "key": "field_6214eddc9d600",
                    "label": "Email",
                    "name": "email",
                    "type": "email",
                    "instructions": "",
                    "required": 1,
                    "conditional_logic": 0,
                    "wrapper": {
                        "width": "",
                        "class": "",
                        "id": ""
                    },
                    "default_value": "",
                    "placeholder": "",
                    "prepend": "",
                    "append": ""
                },
                {
                    "key": "field_6214ee459d601",
                    "label": "Titre newsletter",
                    "name": "title_newsletter",
                    "type": "text",
                    "instructions": "",
                    "required": 1,
                    "conditional_logic": 0,
                    "wrapper": {
                        "width": "",
                        "class": "",
                        "id": ""
                    },
                    "default_value": "",
                    "placeholder": "",
                    "prepend": "",
                    "append": "",
                    "maxlength": ""
                }
            ]
        },
        {
            "key": "field_6220f489e70de",
            "label": "Page Références",
            "name": "",
            "type": "tab",
            "instructions": "",
            "required": 0,
            "conditional_logic": 0,
            "wrapper": {
                "width": "",
                "class": "",
                "id": ""
            },
            "placement": "top",
            "endpoint": 0
        },
        {
            "key": "field_6220f4a6e70df",
            "label": "Titre du bandeau",
            "name": "banner_references_title",
            "type": "textarea",
            "instructions": "",
            "required": 1,
            "conditional_logic": 0,
            "wrapper": {
                "width": "",
                "class": "",
                "id": ""
            },
            "default_value": "",
            "placeholder": "",
            "maxlength": "",
            "rows": 4,
            "new_lines": "br"
        },
        {
            "key": "field_6220f50ee70e0",
            "label": "Texte d'intro du bandeau",
            "name": "banner_references_text",
            "type": "wysiwyg",
            "instructions": "",
            "required": 1,
            "conditional_logic": 0,
            "wrapper": {
                "width": "",
                "class": "",
                "id": ""
            },
            "default_value": "",
            "tabs": "all",
            "toolbar": "full",
            "media_upload": 0,
            "delay": 0
        },
        {
            "key": "field_6221df22c700e",
            "label": "Page Actualités",
            "name": "",
            "type": "tab",
            "instructions": "",
            "required": 0,
            "conditional_logic": 0,
            "wrapper": {
                "width": "",
                "class": "",
                "id": ""
            },
            "placement": "top",
            "endpoint": 0
        },
        {
            "key": "field_6221df33c700f",
            "label": "Titre du bandeau",
            "name": "banner_news_title",
            "type": "textarea",
            "instructions": "",
            "required": 1,
            "conditional_logic": 0,
            "wrapper": {
                "width": "",
                "class": "",
                "id": ""
            },
            "default_value": "",
            "placeholder": "",
            "maxlength": "",
            "rows": 4,
            "new_lines": "br"
        },
        {
            "key": "field_6221df4fc7010",
            "label": "Texte d'intro du bandeau",
            "name": "banner_news_text",
            "type": "wysiwyg",
            "instructions": "",
            "required": 1,
            "conditional_logic": 0,
            "wrapper": {
                "width": "",
                "class": "",
                "id": ""
            },
            "default_value": "",
            "tabs": "all",
            "toolbar": "full",
            "media_upload": 0,
            "delay": 0
        },
        {
            "key": "field_613749c95c6c7",
            "label": "Page Contact",
            "name": "",
            "type": "tab",
            "instructions": "",
            "required": 0,
            "conditional_logic": 0,
            "wrapper": {
                "width": "",
                "class": "",
                "id": ""
            },
            "placement": "top",
            "endpoint": 0
        },
        {
            "key": "field_61578b6df41f7",
            "label": "Choix du formulaire",
            "name": "gf_form_id",
            "type": "select",
            "instructions": "",
            "required": 1,
            "conditional_logic": 0,
            "wrapper": {
                "width": "",
                "class": "",
                "id": ""
            },
            "choices": {
                "1": "Contact"
            },
            "default_value": false,
            "allow_null": 0,
            "multiple": 0,
            "ui": 0,
            "return_format": "value",
            "ajax": 0,
            "placeholder": ""
        }
    ],
    "location": [
        [
            {
                "param": "options_page",
                "operator": "==",
                "value": "theme-general-settings"
            }
        ]
    ],
    "menu_order": 0,
    "position": "normal",
    "style": "default",
    "label_placement": "top",
    "instruction_placement": "label",
    "hide_on_screen": "",
    "active": true,
    "description": "",
    "modified": 1647424380
}